Downsizer.sv
module axis_dwidth_downsizer #(
  parameter WIDTH      = 32, // output width
  parameter NUM_REG    =  2 // Scale factor
)(
    input  logic aclk,                    // input wire aclk
    input  logic aresetn,              // input wire aresetn
    input  logic s_axis_tvalid,  // input wire s_axis_tvalid
    output logic s_axis_tready,  // output wire s_axis_tready
    input  logic [WIDTH*NUM_REG-1:0] s_axis_tdata,    // input wire [63 : 0] s_axis_tdata
    input  logic s_axis_tlast,   

    output logic m_axis_tvalid,  // output wire m_axis_tvalid
    input  logic m_axis_tready,  // input wire m_axis_tready
    output logic [WIDTH-1:0] m_axis_tdata,    // output wire [31 : 0] m_axis_tdata
    output logic m_axis_tlast
);
  // Define the states as enum
    localparam READY = 0;
    localparam SHIFT = 1;
    localparam LAST = 2;

  logic [NUM_REG*WIDTH - 1:0] s_reg;
  logic [32:0] cnt;
  // Define state register and next state variables
  logic [1:0] state_reg;
//   logic [1:0] next_state;
    
  always @(posedge aclk) begin
    m_axis_tdata <= s_reg[WIDTH - 1:0];
    if (aresetn == 0) begin
      state_reg       <= READY;
      cnt             <=  0;
      s_axis_tready   <=  1;
      m_axis_tvalid   <=  0;
      s_reg           <= '0;
    end else begin
    //   m_axis_tdata    <= s_reg;
      // State transitions and outputs
      case (state_reg)
        READY:
          begin
            cnt <=  0;
            if (s_axis_tvalid == 1) begin
              s_reg       <= s_axis_tdata;
              state_reg   <= SHIFT;
              s_axis_tready <= 0;
              m_axis_tvalid <= 1;
            end
          end
        SHIFT:
          begin
            if (cnt < NUM_REG - 1  & m_axis_tready == 1) begin
                cnt   <= cnt + 1;
                s_reg <= s_reg >> WIDTH;
            end else if (cnt < NUM_REG - 1 & m_axis_tready == 0) 
                state_reg <= SHIFT;
            else begin
                state_reg <= LAST;
	            m_axis_tvalid <= 0;
	        end
          end
        LAST:
          begin
            if (m_axis_tready == 1) begin
                state_reg     <= READY;
                s_axis_tready <= 1;	
	        end
          end
        
        // Define transitions for other states
      endcase
    end
  end
endmodule

Downsizer_tb.sv
module test;
  localparam WIDTH = 32;
  localparam NUM_REG=2;

  /* Make a reset that pulses once. */
  reg reset = 1;
  initial begin
     # 5 reset = 0;
     # 50 reset = 1;
     # 1000 $stop;
  end

  /* Make a regular pulsing clock. */
  reg clk = 0;
  always #5 clk = !clk;

  reg s_axis_tvalid = 0;
  reg [WIDTH*NUM_REG-1:0] s_axis_tdata = (1 << WIDTH) + 100;
  reg s_axis_tlast = 0;
  reg m_axis_tready = 1;
  initial begin
    #100 s_axis_tvalid = 1;
  end
  always #20 s_axis_tdata = s_axis_tdata + (1 << WIDTH) + 16;

  wire s_axis_tready;
  wire m_axis_tvalid;
  wire [WIDTH-1:0] m_axis_tdata;
  wire m_axis_tlast;
  axis_dwidth_downsizer downsizer (.aclk(clk),                    // input wire aclk
    .aresetn(reset),              // input wire aresetn
    .s_axis_tvalid(s_axis_tvalid),  // input wire s_axis_tvalid
    .s_axis_tready(s_axis_tready),  // output wire s_axis_tready
    .s_axis_tdata(s_axis_tdata),    // input wire [64 : 0] s_axis_tdata
    .s_axis_tlast(s_axis_tlast),   

    .m_axis_tvalid(m_axis_tvalid),  // output wire m_axis_tvalid
    .m_axis_tready(m_axis_tready),  // input wire m_axis_tready
    .m_axis_tdata(m_axis_tdata),    // output wire [32 : 0] m_axis_tdata
    .m_axis_tlast(m_axis_tlast));

  initial begin
    $dumpfile("test_downsizer.vcd");
    $dumpvars(0,test);
    
    // $monitor("At time %t, value = %h (%0d)",
    //           $time, value, value);
  end
endmodule // test

test_downsizer.vcd
$date
	Wed May 24 13:43:54 2023
$end
$version
	Icarus Verilog
$end
$timescale
	1s
$end
$scope module test $end
$var wire 1 ! s_axis_tready $end
$var wire 1 " m_axis_tvalid $end
$var wire 1 # m_axis_tlast $end
$var wire 32 $ m_axis_tdata [31:0] $end
$var reg 1 % clk $end
$var reg 1 & m_axis_tready $end
$var reg 1 ' reset $end
$var reg 64 ( s_axis_tdata [63:0] $end
$var reg 1 ) s_axis_tlast $end
$var reg 1 * s_axis_tvalid $end
$scope module downsizer $end
$var wire 1 % aclk $end
$var wire 1 ' aresetn $end
$var wire 1 & m_axis_tready $end
$var wire 64 + s_axis_tdata [63:0] $end
$var wire 1 ) s_axis_tlast $end
$var wire 1 * s_axis_tvalid $end
$var wire 32 , m_axis_tdata [31:0] $end
$var reg 33 - cnt [32:0] $end
$var reg 1 # m_axis_tlast $end
$var reg 1 " m_axis_tvalid $end
$var reg 1 ! s_axis_tready $end
$var reg 64 . s_reg [63:0] $end
$var reg 2 / state_reg [1:0] $end
$upscope $end
$upscope $end
$enddefinitions $end
#0
$dumpvars
bx /
bx .
bx -
bx ,
b100000000000000000000000001100100 +
0*
0)
b100000000000000000000000001100100 (
1'
1&
0%
bx $
x#
x"
x!
$end
#5
b0 $
b0 ,
b0 .
0"
1!
b0 -
b0 /
1%
0'
#10
0%
#15
1%
#20
0%
b1000000000000000000000000001110100 (
b1000000000000000000000000001110100 +
#25
1%
#30
0%
#35
1%
#40
0%
b1100000000000000000000000010000100 (
b1100000000000000000000000010000100 +
#45
1%
#50
0%
#55
1%
1'
#60
0%
b10000000000000000000000000010010100 (
b10000000000000000000000000010010100 +
#65
1%
#70
0%
#75
1%
#80
0%
b10100000000000000000000000010100100 (
b10100000000000000000000000010100100 +
#85
1%
#90
0%
#95
1%
#100
0%
b11000000000000000000000000010110100 (
b11000000000000000000000000010110100 +
1*
#105
b10110100 $
b10110100 ,
1"
0!
b1 /
b11000000000000000000000000010110100 .
1%
#110
0%
#115
b110 $
b110 ,
b110 .
b1 -
1%
#120
0%
b11100000000000000000000000011000100 (
b11100000000000000000000000011000100 +
#125
0"
b10 /
1%
#130
0%
#135
1!
b0 /
1%
#140
0%
b100000000000000000000000000011010100 (
b100000000000000000000000000011010100 +
#145
b11010100 $
b11010100 ,
1"
0!
b1 /
b100000000000000000000000000011010100 .
b0 -
1%
#150
0%
#155
b1000 $
b1000 ,
b1000 .
b1 -
1%
#160
0%
b100100000000000000000000000011100100 (
b100100000000000000000000000011100100 +
#165
0"
b10 /
1%
#170
0%
#175
1!
b0 /
1%
#180
0%
b101000000000000000000000000011110100 (
b101000000000000000000000000011110100 +
#185
b11110100 $
b11110100 ,
1"
0!
b1 /
b101000000000000000000000000011110100 .
b0 -
1%
#190
0%
#195
b1010 $
b1010 ,
b1010 .
b1 -
1%
#200
0%
b101100000000000000000000000100000100 (
b101100000000000000000000000100000100 +
#205
0"
b10 /
1%
#210
0%
#215
1!
b0 /
1%
#220
0%
b110000000000000000000000000100010100 (
b110000000000000000000000000100010100 +
#225
b100010100 $
b100010100 ,
1"
0!
b1 /
b110000000000000000000000000100010100 .
b0 -
1%
#230
0%
#235
b1100 $
b1100 ,
b1100 .
b1 -
1%
#240
0%
b110100000000000000000000000100100100 (
b110100000000000000000000000100100100 +
#245
0"
b10 /
1%
#250
0%
#255
1!
b0 /
1%
#260
0%
b111000000000000000000000000100110100 (
b111000000000000000000000000100110100 +
#265
b100110100 $
b100110100 ,
1"
0!
b1 /
b111000000000000000000000000100110100 .
b0 -
1%
#270
0%
#275
b1110 $
b1110 ,
b1110 .
b1 -
1%
#280
0%
b111100000000000000000000000101000100 (
b111100000000000000000000000101000100 +
#285
0"
b10 /
1%
#290
0%
#295
1!
b0 /
1%
#300
0%
b1000000000000000000000000000101010100 (
b1000000000000000000000000000101010100 +
#305
b101010100 $
b101010100 ,
1"
0!
b1 /
b1000000000000000000000000000101010100 .
b0 -
1%
#310
0%
#315
b10000 $
b10000 ,
b10000 .
b1 -
1%
#320
0%
b1000100000000000000000000000101100100 (
b1000100000000000000000000000101100100 +
#325
0"
b10 /
1%
#330
0%
#335
1!
b0 /
1%
#340
0%
b1001000000000000000000000000101110100 (
b1001000000000000000000000000101110100 +
#345
b101110100 $
b101110100 ,
1"
0!
b1 /
b1001000000000000000000000000101110100 .
b0 -
1%
#350
0%
#355
b10010 $
b10010 ,
b10010 .
b1 -
1%
#360
0%
b1001100000000000000000000000110000100 (
b1001100000000000000000000000110000100 +
#365
0"
b10 /
1%
#370
0%
#375
1!
b0 /
1%
#380
0%
b1010000000000000000000000000110010100 (
b1010000000000000000000000000110010100 +
#385
b110010100 $
b110010100 ,
1"
0!
b1 /
b1010000000000000000000000000110010100 .
b0 -
1%
#390
0%
#395
b10100 $
b10100 ,
b10100 .
b1 -
1%
#400
0%
b1010100000000000000000000000110100100 (
b1010100000000000000000000000110100100 +
#405
0"
b10 /
1%
#410
0%
#415
1!
b0 /
1%
#420
0%
b1011000000000000000000000000110110100 (
b1011000000000000000000000000110110100 +
#425
b110110100 $
b110110100 ,
1"
0!
b1 /
b1011000000000000000000000000110110100 .
b0 -
1%
#430
0%
#435
b10110 $
b10110 ,
b10110 .
b1 -
1%
#440
0%
b1011100000000000000000000000111000100 (
b1011100000000000000000000000111000100 +
#445
0"
b10 /
1%
#450
0%
#455
1!
b0 /
1%
#460
0%
b1100000000000000000000000000111010100 (
b1100000000000000000000000000111010100 +
#465
b111010100 $
b111010100 ,
1"
0!
b1 /
b1100000000000000000000000000111010100 .
b0 -
1%
#470
0%
#475
b11000 $
b11000 ,
b11000 .
b1 -
1%
#480
0%
b1100100000000000000000000000111100100 (
b1100100000000000000000000000111100100 +
#485
0"
b10 /
1%
#490
0%
#495
1!
b0 /
1%
#500
0%
b1101000000000000000000000000111110100 (
b1101000000000000000000000000111110100 +
#505
b111110100 $
b111110100 ,
1"
0!
b1 /
b1101000000000000000000000000111110100 .
b0 -
1%
#510
0%
#515
b11010 $
b11010 ,
b11010 .
b1 -
1%
#520
0%
b1101100000000000000000000001000000100 (
b1101100000000000000000000001000000100 +
#525
0"
b10 /
1%
#530
0%
#535
1!
b0 /
1%
#540
0%
b1110000000000000000000000001000010100 (
b1110000000000000000000000001000010100 +
#545
b1000010100 $
b1000010100 ,
1"
0!
b1 /
b1110000000000000000000000001000010100 .
b0 -
1%
#550
0%
#555
b11100 $
b11100 ,
b11100 .
b1 -
1%
#560
0%
b1110100000000000000000000001000100100 (
b1110100000000000000000000001000100100 +
#565
0"
b10 /
1%
#570
0%
#575
1!
b0 /
1%
#580
0%
b1111000000000000000000000001000110100 (
b1111000000000000000000000001000110100 +
#585
b1000110100 $
b1000110100 ,
1"
0!
b1 /
b1111000000000000000000000001000110100 .
b0 -
1%
#590
0%
#595
b11110 $
b11110 ,
b11110 .
b1 -
1%
#600
0%
b1111100000000000000000000001001000100 (
b1111100000000000000000000001001000100 +
#605
0"
b10 /
1%
#610
0%
#615
1!
b0 /
1%
#620
0%
b10000000000000000000000000001001010100 (
b10000000000000000000000000001001010100 +
#625
b1001010100 $
b1001010100 ,
1"
0!
b1 /
b10000000000000000000000000001001010100 .
b0 -
1%
#630
0%
#635
b100000 $
b100000 ,
b100000 .
b1 -
1%
#640
0%
b10000100000000000000000000001001100100 (
b10000100000000000000000000001001100100 +
#645
0"
b10 /
1%
#650
0%
#655
1!
b0 /
1%
#660
0%
b10001000000000000000000000001001110100 (
b10001000000000000000000000001001110100 +
#665
b1001110100 $
b1001110100 ,
1"
0!
b1 /
b10001000000000000000000000001001110100 .
b0 -
1%
#670
0%
#675
b100010 $
b100010 ,
b100010 .
b1 -
1%
#680
0%
b10001100000000000000000000001010000100 (
b10001100000000000000000000001010000100 +
#685
0"
b10 /
1%
#690
0%
#695
1!
b0 /
1%
#700
0%
b10010000000000000000000000001010010100 (
b10010000000000000000000000001010010100 +
#705
b1010010100 $
b1010010100 ,
1"
0!
b1 /
b10010000000000000000000000001010010100 .
b0 -
1%
#710
0%
#715
b100100 $
b100100 ,
b100100 .
b1 -
1%
#720
0%
b10010100000000000000000000001010100100 (
b10010100000000000000000000001010100100 +
#725
0"
b10 /
1%
#730
0%
#735
1!
b0 /
1%
#740
0%
b10011000000000000000000000001010110100 (
b10011000000000000000000000001010110100 +
#745
b1010110100 $
b1010110100 ,
1"
0!
b1 /
b10011000000000000000000000001010110100 .
b0 -
1%
#750
0%
#755
b100110 $
b100110 ,
b100110 .
b1 -
1%
#760
0%
b10011100000000000000000000001011000100 (
b10011100000000000000000000001011000100 +
#765
0"
b10 /
1%
#770
0%
#775
1!
b0 /
1%
#780
0%
b10100000000000000000000000001011010100 (
b10100000000000000000000000001011010100 +
#785
b1011010100 $
b1011010100 ,
1"
0!
b1 /
b10100000000000000000000000001011010100 .
b0 -
1%
#790
0%
#795
b101000 $
b101000 ,
b101000 .
b1 -
1%
#800
0%
b10100100000000000000000000001011100100 (
b10100100000000000000000000001011100100 +
#805
0"
b10 /
1%
#810
0%
#815
1!
b0 /
1%
#820
0%
b10101000000000000000000000001011110100 (
b10101000000000000000000000001011110100 +
#825
b1011110100 $
b1011110100 ,
1"
0!
b1 /
b10101000000000000000000000001011110100 .
b0 -
1%
#830
0%
#835
b101010 $
b101010 ,
b101010 .
b1 -
1%
#840
0%
b10101100000000000000000000001100000100 (
b10101100000000000000000000001100000100 +
#845
0"
b10 /
1%
#850
0%
#855
1!
b0 /
1%
#860
0%
b10110000000000000000000000001100010100 (
b10110000000000000000000000001100010100 +
#865
b1100010100 $
b1100010100 ,
1"
0!
b1 /
b10110000000000000000000000001100010100 .
b0 -
1%
#870
0%
#875
b101100 $
b101100 ,
b101100 .
b1 -
1%
#880
0%
b10110100000000000000000000001100100100 (
b10110100000000000000000000001100100100 +
#885
0"
b10 /
1%
#890
0%
#895
1!
b0 /
1%
#900
0%
b10111000000000000000000000001100110100 (
b10111000000000000000000000001100110100 +
#905
b1100110100 $
b1100110100 ,
1"
0!
b1 /
b10111000000000000000000000001100110100 .
b0 -
1%
#910
0%
#915
b101110 $
b101110 ,
b101110 .
b1 -
1%
#920
0%
b10111100000000000000000000001101000100 (
b10111100000000000000000000001101000100 +
#925
0"
b10 /
1%
#930
0%
#935
1!
b0 /
1%
#940
0%
b11000000000000000000000000001101010100 (
b11000000000000000000000000001101010100 +
#945
b1101010100 $
b1101010100 ,
1"
0!
b1 /
b11000000000000000000000000001101010100 .
b0 -
1%
#950
0%
#955
b110000 $
b110000 ,
b110000 .
b1 -
1%
#960
0%
b11000100000000000000000000001101100100 (
b11000100000000000000000000001101100100 +
#965
0"
b10 /
1%
#970
0%
#975
1!
b0 /
1%
#980
0%
b11001000000000000000000000001101110100 (
b11001000000000000000000000001101110100 +
#985
b1101110100 $
b1101110100 ,
1"
0!
b1 /
b11001000000000000000000000001101110100 .
b0 -
1%
#990
0%
#995
b110010 $
b110010 ,
b110010 .
b1 -
1%
#1000
0%
b11001100000000000000000000001110000100 (
b11001100000000000000000000001110000100 +
#1005
0"
b10 /
1%
#1010
0%
#1015
1!
b0 /
1%
#1020
0%
b11010000000000000000000000001110010100 (
b11010000000000000000000000001110010100 +
#1025
b1110010100 $
b1110010100 ,
1"
0!
b1 /
b11010000000000000000000000001110010100 .
b0 -
1%
#1030
0%
#1035
b110100 $
b110100 ,
b110100 .
b1 -
1%
#1040
0%
b11010100000000000000000000001110100100 (
b11010100000000000000000000001110100100 +
#1045
0"
b10 /
1%
