Upsizer.sv
module axis_dwidth_upsizer #(
  parameter WIDTH      = 32, // input width
  parameter NUM_REG    =  2 // Scale factor
)(
    input  logic aclk,                    // input wire aclk
    input  logic aresetn,              // input wire aresetn
    input  logic s_axis_tvalid,  // input wire s_axis_tvalid
    output logic s_axis_tready,  // output wire s_axis_tready
    input  logic [WIDTH-1:0] s_axis_tdata,    // input wire [31 : 0] s_axis_tdata
    input  logic s_axis_tlast,   

    output logic m_axis_tvalid,  // output wire m_axis_tvalid
    input  logic m_axis_tready,  // input wire m_axis_tready
    output logic [WIDTH*NUM_REG-1:0] m_axis_tdata,    // output wire [63 : 0] m_axis_tdata
    output logic m_axis_tlast
);
  // Define the states as enum
    localparam READY = 0;
    localparam LOAD = 1;
    localparam WRTARRAY = 2;

  logic [NUM_REG*WIDTH - 1:0] s_reg;
  logic [32:0] cnt;
  // Define state register and next state variables
  logic [1:0] state_reg;
  logic m_axis_tlast_local;
//   logic [1:0] next_state;
  always @(posedge aclk) begin
    if (aresetn == 0) begin
      state_reg       <= READY;
      cnt             <=  0;
      s_axis_tready   <=  1;
      m_axis_tvalid   <=  0;
      m_axis_tlast    <=  0;
      m_axis_tlast_local <= 0;
      s_reg           <= '0;
    end else begin
      m_axis_tdata    <= s_reg;
      if (s_axis_tlast == 1) m_axis_tlast_local <= 1;
      // State transitions and outputs
      case (state_reg)
        READY:
          begin
            cnt <=  0;
            if (s_axis_tvalid == 1) begin
              s_reg[WIDTH-1:0] <= s_axis_tdata;
              state_reg   <= LOAD;
              cnt           <= cnt + 1;
            end
          end
        LOAD:
          begin
            if (cnt < NUM_REG & m_axis_tlast_local == 1) begin
              s_reg <= (s_reg << WIDTH);
              cnt            <= cnt + 1;
              state_reg      <= LOAD;
            end else if (cnt < NUM_REG  & s_axis_tvalid == 1) begin
              s_reg <= (s_reg << WIDTH) | s_axis_tdata;
              cnt            <= cnt + 1;
              state_reg      <= LOAD;
            end else if (cnt < NUM_REG & s_axis_tvalid == 0) 
              state_reg <= LOAD;
            else begin
              state_reg       <= WRTARRAY;
              s_axis_tready   <= 0;
              m_axis_tvalid   <= 1;
              m_axis_tlast    <= m_axis_tlast_local;
              cnt <= 0;
            end
          end
        WRTARRAY:
          begin
            if (m_axis_tready == 1) begin
              state_reg       <= READY;
              m_axis_tvalid <= 0;
              s_axis_tready   <= 1;
              m_axis_tlast    <= 0;
              m_axis_tlast_local <= 0;
            end
          end
      endcase
    end
  end
endmodule

Upsizer_tb.sv
module test;
  localparam WIDTH = 32;
  localparam NUM_REG=2;

  /* Make a reset that pulses once. */
  reg reset = 1;
  initial begin
     # 5 reset = 0;
     # 50 reset = 1;
     # 300 $stop;
  end

  /* Make a regular pulsing clock. */
  reg clk = 0;
  always #5 clk = !clk;

  reg s_axis_tvalid = 0;
  reg [WIDTH-1:0] s_axis_tdata = 100;
  reg s_axis_tlast = 0;
  reg m_axis_tready = 1;
  initial begin
    #80 s_axis_tvalid = 1;
    #130 s_axis_tlast = 1;
    #10 s_axis_tlast = 0; 
  end
  always #10 s_axis_tdata = s_axis_tdata + 16;

  wire s_axis_tready;
  wire m_axis_tvalid;
  wire [WIDTH*NUM_REG-1:0] m_axis_tdata;
  wire m_axis_tlast;
  axis_dwidth_upsizer upsizer (.aclk(clk),                    // input wire aclk
    .aresetn(reset),              // input wire aresetn
    .s_axis_tvalid(s_axis_tvalid),  // input wire s_axis_tvalid
    .s_axis_tready(s_axis_tready),  // output wire s_axis_tready
    .s_axis_tdata(s_axis_tdata),    // input wire [31 : 0] s_axis_tdata
    .s_axis_tlast(s_axis_tlast),   

    .m_axis_tvalid(m_axis_tvalid),  // output wire m_axis_tvalid
    .m_axis_tready(m_axis_tready),  // input wire m_axis_tready
    .m_axis_tdata(m_axis_tdata),    // output wire [63 : 0] m_axis_tdata
    .m_axis_tlast(m_axis_tlast));

  initial begin
    $dumpfile("test_upsizer.vcd");
    $dumpvars(0,test);
    
    // $monitor("At time %t, value = %h (%0d)",
    //           $time, value, value);
  end
endmodule // test

test_upsizer.vcd
$date
	Wed May 24 14:11:00 2023
$end
$version
	Icarus Verilog
$end
$timescale
	1s
$end
$scope module test $end
$var wire 1 ! s_axis_tready $end
$var wire 1 " m_axis_tvalid $end
$var wire 1 # m_axis_tlast $end
$var wire 64 $ m_axis_tdata [63:0] $end
$var reg 1 % clk $end
$var reg 1 & m_axis_tready $end
$var reg 1 ' reset $end
$var reg 32 ( s_axis_tdata [31:0] $end
$var reg 1 ) s_axis_tlast $end
$var reg 1 * s_axis_tvalid $end
$scope module upsizer $end
$var wire 1 % aclk $end
$var wire 1 ' aresetn $end
$var wire 1 & m_axis_tready $end
$var wire 32 + s_axis_tdata [31:0] $end
$var wire 1 ) s_axis_tlast $end
$var wire 1 * s_axis_tvalid $end
$var reg 33 , cnt [32:0] $end
$var reg 64 - m_axis_tdata [63:0] $end
$var reg 1 # m_axis_tlast $end
$var reg 1 . m_axis_tlast_local $end
$var reg 1 " m_axis_tvalid $end
$var reg 1 ! s_axis_tready $end
$var reg 64 / s_reg [63:0] $end
$var reg 2 0 state_reg [1:0] $end
$upscope $end
$upscope $end
$enddefinitions $end
#0
$dumpvars
bx 0
bx /
x.
bx -
bx ,
b1100100 +
0*
0)
b1100100 (
1'
1&
0%
bx $
x#
x"
x!
$end
#5
b0 /
0.
0#
0"
1!
b0 ,
b0 0
1%
0'
#10
0%
b1110100 (
b1110100 +
#15
1%
#20
0%
b10000100 (
b10000100 +
#25
1%
#30
0%
b10010100 (
b10010100 +
#35
1%
#40
0%
b10100100 (
b10100100 +
#45
1%
#50
0%
b10110100 (
b10110100 +
#55
b0 $
b0 -
1%
1'
#60
0%
b11000100 (
b11000100 +
#65
1%
#70
0%
b11010100 (
b11010100 +
#75
1%
#80
0%
b11100100 (
b11100100 +
1*
#85
b1 ,
b1 0
b11100100 /
1%
#90
0%
b11110100 (
b11110100 +
#95
b10 ,
b1110010000000000000000000000000011110100 /
b11100100 $
b11100100 -
1%
#100
0%
b100000100 (
b100000100 +
#105
b0 ,
1"
0!
b10 0
b1110010000000000000000000000000011110100 $
b1110010000000000000000000000000011110100 -
1%
#110
0%
b100010100 (
b100010100 +
#115
1!
0"
b0 0
1%
#120
0%
b100100100 (
b100100100 +
#125
b1 ,
b1 0
b1110010000000000000000000000000100100100 /
1%
#130
0%
b100110100 (
b100110100 +
#135
b10 ,
b10010010000000000000000000000000100110100 /
b1110010000000000000000000000000100100100 $
b1110010000000000000000000000000100100100 -
1%
#140
0%
b101000100 (
b101000100 +
#145
b0 ,
1"
0!
b10 0
b10010010000000000000000000000000100110100 $
b10010010000000000000000000000000100110100 -
1%
#150
0%
b101010100 (
b101010100 +
#155
1!
0"
b0 0
1%
#160
0%
b101100100 (
b101100100 +
#165
b1 ,
b1 0
b10010010000000000000000000000000101100100 /
1%
#170
0%
b101110100 (
b101110100 +
#175
b10 ,
b10110010000000000000000000000000101110100 /
b10010010000000000000000000000000101100100 $
b10010010000000000000000000000000101100100 -
1%
#180
0%
b110000100 (
b110000100 +
#185
b0 ,
1"
0!
b10 0
b10110010000000000000000000000000101110100 $
b10110010000000000000000000000000101110100 -
1%
#190
0%
b110010100 (
b110010100 +
#195
1!
0"
b0 0
1%
#200
0%
b110100100 (
b110100100 +
#205
b1 ,
b1 0
b10110010000000000000000000000000110100100 /
1%
#210
0%
b110110100 (
b110110100 +
1)
#215
b10 ,
b11010010000000000000000000000000110110100 /
1.
b10110010000000000000000000000000110100100 $
b10110010000000000000000000000000110100100 -
1%
#220
0%
b111000100 (
b111000100 +
0)
#225
b0 ,
1#
1"
0!
b10 0
b11010010000000000000000000000000110110100 $
b11010010000000000000000000000000110110100 -
1%
#230
0%
b111010100 (
b111010100 +
#235
0.
0#
1!
0"
b0 0
1%
#240
0%
b111100100 (
b111100100 +
#245
b1 ,
b1 0
b11010010000000000000000000000000111100100 /
1%
#250
0%
b111110100 (
b111110100 +
#255
b10 ,
b11110010000000000000000000000000111110100 /
b11010010000000000000000000000000111100100 $
b11010010000000000000000000000000111100100 -
1%
#260
0%
b1000000100 (
b1000000100 +
#265
b0 ,
1"
0!
b10 0
b11110010000000000000000000000000111110100 $
b11110010000000000000000000000000111110100 -
1%
#270
0%
b1000010100 (
b1000010100 +
#275
1!
0"
b0 0
1%
#280
0%
b1000100100 (
b1000100100 +
#285
b1 ,
b1 0
b11110010000000000000000000000001000100100 /
1%
#290
0%
b1000110100 (
b1000110100 +
#295
b10 ,
b100010010000000000000000000000001000110100 /
b11110010000000000000000000000001000100100 $
b11110010000000000000000000000001000100100 -
1%
#300
0%
b1001000100 (
b1001000100 +
#305
b0 ,
1"
0!
b10 0
b100010010000000000000000000000001000110100 $
b100010010000000000000000000000001000110100 -
1%
#310
0%
b1001010100 (
b1001010100 +
#315
1!
0"
b0 0
1%
#320
0%
b1001100100 (
b1001100100 +
#325
b1 ,
b1 0
b100010010000000000000000000000001001100100 /
1%
#330
0%
b1001110100 (
b1001110100 +
#335
b10 ,
b100110010000000000000000000000001001110100 /
b100010010000000000000000000000001001100100 $
b100010010000000000000000000000001001100100 -
1%
#340
0%
b1010000100 (
b1010000100 +
#345
b0 ,
1"
0!
b10 0
b100110010000000000000000000000001001110100 $
b100110010000000000000000000000001001110100 -
1%
#350
0%
b1010010100 (
b1010010100 +
