Upsizer.sv
module axis_dwidth_upsizer #(
  parameter WIDTH      = 32, // input width
  parameter NUM_REG    =  2 // Scale factor
)(
    input  logic aclk,                    // input wire aclk
    input  logic aresetn,              // input wire aresetn
    input  logic s_axis_tvalid,  // input wire s_axis_tvalid
    output logic s_axis_tready,  // output wire s_axis_tready
    input  logic [WIDTH-1:0] s_axis_tdata,    // input wire [31 : 0] s_axis_tdata
    input  logic s_axis_tlast,   

    output logic m_axis_tvalid,  // output wire m_axis_tvalid
    input  logic m_axis_tready,  // input wire m_axis_tready
    output logic [WIDTH*NUM_REG-1:0] m_axis_tdata,    // output wire [63 : 0] m_axis_tdata
    output logic m_axis_tlast
);
  // Define the states as enum
    localparam READY = 0;
    localparam LOAD = 1;
    localparam WRTARRAY = 2;

  logic [NUM_REG*WIDTH - 1:0] s_reg;
  logic [32:0] cnt;
  // Define state register and next state variables
  logic [1:0] state_reg;
  logic m_axis_tlast_local;
//   logic [1:0] next_state;
  always @(posedge aclk) begin
    if (aresetn == 0) begin
      state_reg       <= READY;
      cnt             <=  0;
      s_axis_tready   <=  1;
      m_axis_tvalid   <=  0;
      m_axis_tlast    <=  0;
      m_axis_tlast_local <= 0;
      s_reg           <= '0;
    end else begin
      m_axis_tdata    <= s_reg;
      if (s_axis_tlast == 1) m_axis_tlast_local <= 1;
      // State transitions and outputs
      case (state_reg)
        READY:
          begin
            cnt <=  0;
            if (s_axis_tvalid == 1) begin
              s_reg[WIDTH-1:0] <= s_axis_tdata;
              state_reg   <= LOAD;
              cnt           <= cnt + 1;
            end
          end
        LOAD:
          begin
            if (cnt < NUM_REG & m_axis_tlast_local == 1) begin
              s_reg <= (s_reg << WIDTH);
              cnt            <= cnt + 1;
              state_reg      <= LOAD;
            end else if (cnt < NUM_REG  & s_axis_tvalid == 1) begin
              s_reg <= (s_reg << WIDTH) | s_axis_tdata;
              cnt            <= cnt + 1;
              state_reg      <= LOAD;
            end else if (cnt < NUM_REG & s_axis_tvalid == 0) 
              state_reg <= LOAD;
            else begin
              state_reg       <= WRTARRAY;
              s_axis_tready   <= 0;
              m_axis_tvalid   <= 1;
              m_axis_tlast    <= m_axis_tlast_local;
              cnt <= 0;
            end
          end
        WRTARRAY:
          begin
            if (m_axis_tready == 1) begin
              state_reg       <= READY;
              m_axis_tvalid <= 0;
              s_axis_tready   <= 1;
              m_axis_tlast    <= 0;
              m_axis_tlast_local <= 0;
            end
          end
      endcase
    end
  end
endmodule

Upsizer_tb.sv
module test;
  localparam WIDTH = 32;
  localparam NUM_REG=2;

  /* Make a reset that pulses once. */
  reg reset = 1;
  initial begin
     # 5 reset = 0;
     # 50 reset = 1;
     # 300 $stop;
  end

  /* Make a regular pulsing clock. */
  reg clk = 0;
  always #5 clk = !clk;

  reg s_axis_tvalid = 0;
  reg [WIDTH-1:0] s_axis_tdata = 100;
  reg s_axis_tlast = 0;
  reg m_axis_tready = 1;
  initial begin
    #80 s_axis_tvalid = 1;
    #130 s_axis_tlast = 1;
    #10 s_axis_tlast = 0; 
  end
  always #10 s_axis_tdata = s_axis_tdata + 16;

  wire s_axis_tready;
  wire m_axis_tvalid;
  wire [WIDTH*NUM_REG-1:0] m_axis_tdata;
  wire m_axis_tlast;
  axis_dwidth_upsizer upsizer (.aclk(clk),                    // input wire aclk
    .aresetn(reset),              // input wire aresetn
    .s_axis_tvalid(s_axis_tvalid),  // input wire s_axis_tvalid
    .s_axis_tready(s_axis_tready),  // output wire s_axis_tready
    .s_axis_tdata(s_axis_tdata),    // input wire [31 : 0] s_axis_tdata
    .s_axis_tlast(s_axis_tlast),   

    .m_axis_tvalid(m_axis_tvalid),  // output wire m_axis_tvalid
    .m_axis_tready(m_axis_tready),  // input wire m_axis_tready
    .m_axis_tdata(m_axis_tdata),    // output wire [63 : 0] m_axis_tdata
    .m_axis_tlast(m_axis_tlast));

  initial begin
    $dumpfile("test_upsizer.vcd");
    $dumpvars(0,test);
    
    // $monitor("At time %t, value = %h (%0d)",
    //           $time, value, value);
  end
endmodule // test

test_upsizer.vcd
$date
	Wed May 24 14:11:00 2023
$end
$version
	Icarus Verilog
$end
$timescale
	1s
$end
$scope module test $end
$var wire 1 ! s_axis_tready $end
$var wire 1 " m_axis_tvalid $end
$var wire 1 # m_axis_tlast $end
$var wire 64 $ m_axis_tdata [63:0] $end
$var reg 1 % clk $end
$var reg 1 & m_axis_tready $end
$var reg 1 ' reset $end
$var reg 32 ( s_axis_tdata [31:0] $end
$var reg 1 ) s_axis_tlast $end
$var reg 1 * s_axis_tvalid $end
$scope module upsizer $end
$var wire 1 % aclk $end
$var wire 1 ' aresetn $end
$var wire 1 & m_axis_tready $end
$var wire 32 + s_axis_tdata [31:0] $end
$var wire 1 ) s_axis_tlast $end
$var wire 1 * s_axis_tvalid $end
$var reg 33 , cnt [32:0] $end
$var reg 64 - m_axis_tdata [63:0] $end
$var reg 1 # m_axis_tlast $end
$var reg 1 . m_axis_tlast_local $end
$var reg 1 " m_axis_tvalid $end
$var reg 1 ! s_axis_tready $end
$var reg 64 / s_reg [63:0] $end
$var reg 2 0 state_reg [1:0] $end
$upscope $end
$upscope $end
$enddefinitions $end
#0
$dumpvars
bx 0
bx /
x.
bx -
bx ,
b1100100 +
0*
0)
b1100100 (
1'
1&
0%
bx $
x#
x"
x!
$end
#5
b0 /
0.
0#
0"
1!
b0 ,
b0 0
1%
0'
#10
0%
b1110100 (
b1110100 +
#15
1%
#20
0%
b10000100 (
b10000100 +
#25
1%
#30
0%
b10010100 (
b10010100 +
#35
1%
#40
0%
b10100100 (
b10100100 +
#45
1%
#50
0%
b10110100 (
b10110100 +
#55
b0 $
b0 -
1%
1'
#60
0%
b11000100 (
b11000100 +
#65
1%
#70
0%
b11010100 (
b11010100 +
#75
1%
#80
0%
b11100100 (
b11100100 +
1*
#85
b1 ,
b1 0
b11100100 /
1%
#90
0%
b11110100 (
b11110100 +
#95
b10 ,
b1110010000000000000000000000000011110100 /
b11100100 $
b11100100 -
1%
#100
0%
b100000100 (
b100000100 +
#105
b0 ,
1"
0!
b10 0
b1110010000000000000000000000000011110100 $
b1110010000000000000000000000000011110100 -
1%
#110
0%
b100010100 (
b100010100 +
#115
1!
0"
b0 0
1%
#120
0%
b100100100 (
b100100100 +
#125
b1 ,
b1 0
b1110010000000000000000000000000100100100 /
1%
#130
0%
b100110100 (
b100110100 +
#135
b10 ,
b10010010000000000000000000000000100110100 /
b1110010000000000000000000000000100100100 $
b1110010000000000000000000000000100100100 -
1%
#140
0%
b101000100 (
b101000100 +
#145
b0 ,
1"
0!
b10 0
b10010010000000000000000000000000100110100 $
b10010010000000000000000000000000100110100 -
1%
#150
0%
b101010100 (
b101010100 +
#155
1!
0"
b0 0
1%
#160
0%
b101100100 (
b101100100 +
#165
b1 ,
b1 0
b10010010000000000000000000000000101100100 /
1%
#170
0%
b101110100 (
b101110100 +
#175
b10 ,
b10110010000000000000000000000000101110100 /
b10010010000000000000000000000000101100100 $
b10010010000000000000000000000000101100100 -
1%
#180
0%
b110000100 (
b110000100 +
#185
b0 ,
1"
0!
b10 0
b10110010000000000000000000000000101110100 $
b10110010000000000000000000000000101110100 -
1%
#190
0%
b110010100 (
b110010100 +
#195
1!
0"
b0 0
1%
#200
0%
b110100100 (
b110100100 +
#205
b1 ,
b1 0
b10110010000000000000000000000000110100100 /
1%
#210
0%
b110110100 (
b110110100 +
1)
#215
b10 ,
b11010010000000000000000000000000110110100 /
1.
b10110010000000000000000000000000110100100 $
b10110010000000000000000000000000110100100 -
1%
#220
0%
b111000100 (
b111000100 +
0)
#225
b0 ,
1#
1"
0!
b10 0
b11010010000000000000000000000000110110100 $
b11010010000000000000000000000000110110100 -
1%
#230
0%
b111010100 (
b111010100 +
#235
0.
0#
1!
0"
b0 0
1%
#240
0%
b111100100 (
b111100100 +
#245
b1 ,
b1 0
b11010010000000000000000000000000111100100 /
1%
#250
0%
b111110100 (
b111110100 +
#255
b10 ,
b11110010000000000000000000000000111110100 /
b11010010000000000000000000000000111100100 $
b11010010000000000000000000000000111100100 -
1%
#260
0%
b1000000100 (
b1000000100 +
#265
b0 ,
1"
0!
b10 0
b11110010000000000000000000000000111110100 $
b11110010000000000000000000000000111110100 -
1%
#270
0%
b1000010100 (
b1000010100 +
#275
1!
0"
b0 0
1%
#280
0%
b1000100100 (
b1000100100 +
#285
b1 ,
b1 0
b11110010000000000000000000000001000100100 /
1%
#290
0%
b1000110100 (
b1000110100 +
#295
b10 ,
b100010010000000000000000000000001000110100 /
b11110010000000000000000000000001000100100 $
b11110010000000000000000000000001000100100 -
1%
#300
0%
b1001000100 (
b1001000100 +
#305
b0 ,
1"
0!
b10 0
b100010010000000000000000000000001000110100 $
b100010010000000000000000000000001000110100 -
1%
#310
0%
b1001010100 (
b1001010100 +
#315
1!
0"
b0 0
1%
#320
0%
b1001100100 (
b1001100100 +
#325
b1 ,
b1 0
b100010010000000000000000000000001001100100 /
1%
#330
0%
b1001110100 (
b1001110100 +
#335
b10 ,
b100110010000000000000000000000001001110100 /
b100010010000000000000000000000001001100100 $
b100010010000000000000000000000001001100100 -
1%
#340
0%
b1010000100 (
b1010000100 +
#345
b0 ,
1"
0!
b10 0
b100110010000000000000000000000001001110100 $
b10011001000000000000000000#355
01001110100 -
1%
#350
0%
b1010010100 (
b1010010#355

#355
1!
0"
b#355
%
#3#355

#355
100100 (
b1010100100 +
#365
b1 ,
b1 0
b100110010000000000000000000000001010100100 /
1%
#370
0%
b1010110100 (
b1010110100 +
#375
b10 ,
b101010010000000000000000000000001010110100 /
b100110010000000000000000000000001010100100 $
b100110010000000000000000000000001010100100 -
1%
#380
0%
b1011000100 (
b1011000100 +
#385
b0 ,
1"
0!
b10 0
b101010010000000000000000000000001010110100 $
b101010010000000000000000000000001010110100 -
1%
#390
0%
b1011010100 (
b1011010100 +
#395
1!
0"
b0 0
1%
#400
0%
b1011100100 (
b1011100100 +
#405
b1 ,
b1 0
b101010010000000000000000000000001011100100 /
1%
#410
0%
b1011110100 (
b1011110100 +
#415
b10 ,
b101110010000000000000000000000001011110100 /
b101010010000000000000000000000001011100100 $
b101010010000000000000000000000001011100100 -
1%
#420
0%
b1100000100 (
b1100000100 +
#425
b0 ,
1"
0!
b10 0
b101110010000000000000000000000001011110100 $
b101110010000000000000000000000001011110100 -
1%
#430
0%
b1100010100 (
b1100010100 +
#435
1!
0"
b0 0
1%
#440
0%
b1100100100 (
b1100100100 +
#445
b1 ,
b1 0
b101110010000000000000000000000001100100100 /
1%
#450
0%
b1100110100 (
b1100110100 +
#455
b10 ,
b110010010000000000000000000000001100110100 /
b101110010000000000000000000000001100100100 $
b101110010000000000000000000000001100100100 -
1%
#460
0%
b1101000100 (
b1101000100 +
#465
b0 ,
1"
0!
b10 0
b110010010000000000000000000000001100110100 $
b110010010000000000000000000000001100110100 -
1%
#470
0%
b1101010100 (
b1101010100 +
#475
1!
0"
b0 0
1%
#480
0%
b1101100100 (
b1101100100 +
#485
b1 ,
b1 0
b110010010000000000000000000000001101100100 /
1%
#490
0%
b1101110100 (
b1101110100 +
#495
b10 ,
b110110010000000000000000000000001101110100 /
b110010010000000000000000000000001101100100 $
b110010010000000000000000000000001101100100 -
1%
#500
0%
b1110000100 (
b1110000100 +
#505
b0 ,
1"
0!
b10 0
b110110010000000000000000000000001101110100 $
b110110010000000000000000000000001101110100 -
1%
#510
0%
b1110010100 (
b1110010100 +
#515
1!
0"
b0 0
1%
#520
0%
b1110100100 (
b1110100100 +
#525
b1 ,
b1 0
b110110010000000000000000000000001110100100 /
1%
#530
0%
b1110110100 (
b1110110100 +
#535
b10 ,
b111010010000000000000000000000001110110100 /
b110110010000000000000000000000001110100100 $
b110110010000000000000000000000001110100100 -
1%
#540
0%
b1111000100 (
b1111000100 +
#545
b0 ,
1"
0!
b10 0
b111010010000000000000000000000001110110100 $
b111010010000000000000000000000001110110100 -
1%
#550
0%
b1111010100 (
b1111010100 +
#555
1!
0"
b0 0
1%
#560
0%
b1111100100 (
b1111100100 +
#565
b1 ,
b1 0
b111010010000000000000000000000001111100100 /
1%
#570
0%
b1111110100 (
b1111110100 +
#575
b10 ,
b111110010000000000000000000000001111110100 /
b111010010000000000000000000000001111100100 $
b111010010000000000000000000000001111100100 -
1%
#580
0%
b10000000100 (
b10000000100 +
#585
b0 ,
1"
0!
b10 0
b111110010000000000000000000000001111110100 $
b111110010000000000000000000000001111110100 -
1%
#590
0%
b10000010100 (
b10000010100 +
#595
1!
0"
b0 0
1%
#600
0%
b10000100100 (
b10000100100 +
#605
b1 ,
b1 0
b111110010000000000000000000000010000100100 /
1%
#610
0%
b10000110100 (
b10000110100 +
#615
b10 ,
b1000010010000000000000000000000010000110100 /
b111110010000000000000000000000010000100100 $
b111110010000000000000000000000010000100100 -
1%
#620
0%
b10001000100 (
b10001000100 +
#625
b0 ,
1"
0!
b10 0
b1000010010000000000000000000000010000110100 $
b1000010010000000000000000000000010000110100 -
1%
#630
0%
b10001010100 (
b10001010100 +
#635
1!
0"
b0 0
1%
#640
0%
b10001100100 (
b10001100100 +
#645
b1 ,
b1 0
b1000010010000000000000000000000010001100100 /
1%
#650
0%
b10001110100 (
b10001110100 +
#655
b10 ,
b1000110010000000000000000000000010001110100 /
b1000010010000000000000000000000010001100100 $
b1000010010000000000000000000000010001100100 -
1%
#660
0%
b10010000100 (
b10010000100 +
#665
b0 ,
1"
0!
b10 0
b1000110010000000000000000000000010001110100 $
b1000110010000000000000000000000010001110100 -
1%
#670
0%
b10010010100 (
b10010010100 +
#675
1!
0"
b0 0
1%
#680
0%
b10010100100 (
b10010100100 +
#685
b1 ,
b1 0
b1000110010000000000000000000000010010100100 /
1%
#690
0%
b10010110100 (
b10010110100 +
#695
b10 ,
b1001010010000000000000000000000010010110100 /
b1000110010000000000000000000000010010100100 $
b1000110010000000000000000000000010010100100 -
1%
#700
0%
b10011000100 (
b10011000100 +
#705
b0 ,
1"
0!
b10 0
b1001010010000000000000000000000010010110100 $
b1001010010000000000000000000000010010110100 -
1%
#710
0%
b10011010100 (
b10011010100 +
#715
1!
0"
b0 0
1%
#720
0%
b10011100100 (
b10011100100 +
#725
b1 ,
b1 0
b1001010010000000000000000000000010011100100 /
1%
#730
0%
b10011110100 (
b10011110100 +
#735
b10 ,
b1001110010000000000000000000000010011110100 /
b1001010010000000000000000000000010011100100 $
b1001010010000000000000000000000010011100100 -
1%
#740
0%
b10100000100 (
b10100000100 +
#745
b0 ,
1"
0!
b10 0
b1001110010000000000000000000000010011110100 $
b1001110010000000000000000000000010011110100 -
1%
#750
0%
b10100010100 (
b10100010100 +
#755
1!
0"
b0 0
1%
#760
0%
b10100100100 (
b10100100100 +
#765
b1 ,
b1 0
b1001110010000000000000000000000010100100100 /
1%
#770
0%
b10100110100 (
b10100110100 +
#775
b10 ,
b1010010010000000000000000000000010100110100 /
b1001110010000000000000000000000010100100100 $
b1001110010000000000000000000000010100100100 -
1%
#780
0%
b10101000100 (
b10101000100 +
#785
b0 ,
1"
0!
b10 0
b1010010010000000000000000000000010100110100 $
b1010010010000000000000000000000010100110100 -
1%
#790
0%
b10101010100 (
b10101010100 +
#795
1!
0"
b0 0
1%
#800
0%
b10101100100 (
b10101100100 +
#805
b1 ,
b1 0
b1010010010000000000000000000000010101100100 /
1%
#810
0%
b10101110100 (
b10101110100 +
#815
b10 ,
b1010110010000000000000000000000010101110100 /
b1010010010000000000000000000000010101100100 $
b1010010010000000000000000000000010101100100 -
1%
#820
0%
b10110000100 (
b10110000100 +
#825
b0 ,
1"
0!
b10 0
b1010110010000000000000000000000010101110100 $
b1010110010000000000000000000000010101110100 -
1%
#830
0%
b10110010100 (
b10110010100 +
#835
1!
0"
b0 0
1%
#840
0%
b10110100100 (
b10110100100 +
#845
b1 ,
b1 0
b1010110010000000000000000000000010110100100 /
1%
#850
0%
b10110110100 (
b10110110100 +
#855
b10 ,
b1011010010000000000000000000000010110110100 /
b1010110010000000000000000000000010110100100 $
b1010110010000000000000000000000010110100100 -
1%
#860
0%
b10111000100 (
b10111000100 +
#865
b0 ,
1"
0!
b10 0
b1011010010000000000000000000000010110110100 $
b1011010010000000000000000000000010110110100 -
1%
#870
0%
b10111010100 (
b10111010100 +
#875
1!
0"
b0 0
1%
#880
0%
b10111100100 (
b10111100100 +
#885
b1 ,
b1 0
b1011010010000000000000000000000010111100100 /
1%
#890
0%
b10111110100 (
b10111110100 +
#895
b10 ,
b1011110010000000000000000000000010111110100 /
b1011010010000000000000000000000010111100100 $
b1011010010000000000000000000000010111100100 -
1%
#900
0%
b11000000100 (
b11000000100 +
#905
b0 ,
1"
0!
b10 0
b1011110010000000000000000000000010111110100 $
b1011110010000000000000000000000010111110100 -
1%
#910
0%
b11000010100 (
b11000010100 +
#915
1!
0"
b0 0
1%
#920
0%
b11000100100 (
b11000100100 +
#925
b1 ,
b1 0
b1011110010000000000000000000000011000100100 /
1%
#930
0%
b11000110100 (
b11000110100 +
#935
b10 ,
b1100010010000000000000000000000011000110100 /
b1011110010000000000000000000000011000100100 $
b1011110010000000000000000000000011000100100 -
1%
#940
0%
b11001000100 (
b11001000100 +
#945
b0 ,
1"
0!
b10 0
b1100010010000000000000000000000011000110100 $
b1100010010000000000000000000000011000110100 -
1%
#950
0%
b11001010100 (
b11001010100 +
#955
1!
0"
b0 0
1%
#960
0%
b11001100100 (
b11001100100 +
#965
b1 ,
b1 0
b1100010010000000000000000000000011001100100 /
1%
#970
0%
b11001110100 (
b11001110100 +
#975
b10 ,
b1100110010000000000000000000000011001110100 /
b1100010010000000000000000000000011001100100 $
b1100010010000000000000000000000011001100100 -
1%
#980
0%
b11010000100 (
b11010000100 +
#985
b0 ,
1"
0!
b10 0
b1100110010000000000000000000000011001110100 $
b1100110010000000000000000000000011001110100 -
1%
#990
0%
b11010010100 (
b11010010100 +
#995
1!
0"
b0 0
1%
#1000
0%
b11010100100 (
b11010100100 +
#1005
b1 ,
b1 0
b1100110010000000000000000000000011010100100 /
1%
#1010
0%
b11010110100 (
b11010110100 +
#1015
b10 ,
b1101010010000000000000000000000011010110100 /
b1100110010000000000000000000000011010100100 $
b1100110010000000000000000000000011010100100 -
1%
#1020
0%
b11011000100 (
b11011000100 +
#1025
b0 ,
1"
0!
b10 0
b1101010010000000000000000000000011010110100 $
b1101010010000000000000000000000011010110100 -
1%
#1030
0%
b11011010100 (
b11011010100 +
#1035
1!
0"
b0 0
1%
#1040
0%
b11011100100 (
b11011100#1055
#1045
b1 ,
b1 0
b1101010010000000000000000000000011011100100 /
1%
#1050
0%
b11011110100 (
b11011110100 +
#1055
b10 ,
b1101110010000000000000000000000011011110100 /
b1101010010000000000000000000000011011100100 $
b1101010010000000000000000000000011011100100 -
1%
#1060
0%
b11100000100 (
b11100000100 +
#1065
b0 ,
1"
0!
b10 0
b1101110010000000000000000000000011011110100 $
b1101110010000000000000000000000011011110100 -
1%
#1070
0%
b11100010100 (
b11100010100 +
#1075
1!
0"
b0 0
1%
#1080
0%
b11100100100 (
b11100100100 +
#1085
b1 ,
b1 0
b1101110010000000000000000000000011100100100 /
1%
#1090
0%
b11100110100 (
b11100110100 +
#1095
b10 ,
b1110010010000000000000000000000011100110100 /
b1101110010000000000000000000000011100100100 $
b1101110010000000000000000000000011100100100 -
1%
#1100
0%
b11101000100 (
b11101000100 +
#1105
b0 ,
1"
0!
b10 0
b1110010010000000000000000000000011100110100 $
b1110010010000000000000000000000011100110100 -
1%
#1110
0%
b11101010100 (
b11101010100 +
#1115
1!
0"
b0 0
1%
#1120
0%
b11101100100 (
b11101100100 +
#1125
b1 ,
b1 0
b1110010010000000000000000000000011101100100 /
1%
#1130
0%
b11101110100 (
b11101110100 +
#1135
b10 ,
b1110110010000000000000000000000011101110100 /
b1110010010000000000000000000000011101100100 $
b1110010010000000000000000000000011101100100 -
1%
#1140
0%
b11110000100 (
b11110000100 +
#1145
b0 ,
1"
0!
b10 0
b1110110010000000000000000000000011101110100 $
b1110110010000000000000000000000011101110100 -
1%
#1150
0%
b11110010100 (
b11110010100 +
#1155
1!
0"
b0 0
1%
#1160
0%
b11110100100 (
b11110100100 +
#1165
b1 ,
b1 0
b1110110010000000000000000000000011110100100 /
1%
#1170
0%
b11110110100 (
b11110110100 +
#1175
b10 ,
b1111010010000000000000000000000011110110100 /
b1110110010000000000000000000000011110100100 $
b1110110010000000000000000000000011110100100 -
1%
#1180
0%
b11111000100 (
b11111000100 +
#1185
b0 ,
1"
0!
b10 0
b1111010010000000000000000000000011110110100 $
b1111010010000000000000000000000011110110100 -
1%
#1190
0%
b11111010100 (
b11111010100 +
#1195
1!
0"
b0 0
1%
#1200
0%
b11111100100 (
b11111100100 +
#1205
b1 ,
b1 0
b1111010010000000000000000000000011111100100 /
1%
#1210
0%
b11111110100 (
b11111110100 +
#1215
b10 ,
b1111110010000000000000000000000011111110100 /
b1111010010000000000000000000000011111100100 $
b1111010010000000000000000000000011111100100 -
1%
#1220
0%
b100000000100 (
b100000000100 +
#1225
b0 ,
1"
0!
b10 0
b1111110010000000000000000000000011111110100 $
b1111110010000000000000000000000011111110100 -
1%
#1230
0%
b100000010100 (
b100000010100 +
#1235
1!
0"
b0 0
1%
#1240
0%
b100000100100 (
b100000100100 +
#1245
b1 ,
b1 0
b1111110010000000000000000000000100000100100 /
1%
#1250
0%
b100000110100 (
b100000110100 +
#1255
b10 ,
b10000010010000000000000000000000100000110100 /
b1111110010000000000000000000000100000100100 $
b1111110010000000000000000000000100000100100 -
1%
#1260
0%
b100001000100 (
b100001000100 +
#1265
b0 ,
1"
0!
b10 0
b10000010010000000000000000000000100000110100 $
b10000010010000000000000000000000100000110100 -
1%
#1270
0%
b100001010100 (
b100001010100 +
#1275
1!
0"
b0 0
1%
#1280
0%
b100001100100 (
b100001100100 +
#1285
b1 ,
b1 0
b10000010010000000000000000000000100001100100 /
1%
#1290
0%
b100001110100 (
b100001110100 +
#1295
b10 ,
b10000110010000000000000000000000100001110100 /
b10000010010000000000000000000000100001100100 $
b10000010010000000000000000000000100001100100 -
1%
#1300
0%
b100010000100 (
b100010000100 +
#1305
b0 ,
1"
0!
b10 0
b10000110010000000000000000000000100001110100 $
b10000110010000000000000000000000100001110100 -
1%
#1310
0%
b100010010100 (
b100010010100 +
#1315
1!
0"
b0 0
1%
#1320
0%
b100010100100 (
b100010100100 +
#1325
b1 ,
b1 0
b10000110010000000000000000000000100010100100 /
1%
#1330
0%
b100010110100 (
b100010110100 +
#1335
b10 ,
b10001010010000000000000000000000100010110100 /
b10000110010000000000000000000000100010100100 $
b10000110010000000000000000000000100010100100 -
1%
#1340
0%
b100011000100 (
b100011000100 +
#1345
b0 ,
1"
0!
b10 0
b10001010010000000000000000000000100010110100 $
b10001010010000000000000000000000100010110100 -
1%
#1350
0%
b100011010100 (
b100011010100 +
#1355
1!
0"
b0 0
1%
#1360
0%
b100011100100 (
b100011100100 +
#1365
b1 ,
b1 0
b10001010010000000000000000000000100011100100 /
1%
#1370
0%
b100011110100 (
b100011110100 +
#1375
b10 ,
b10001110010000000000000000000000100011110100 /
b10001010010000000000000000000000100011100100 $
b10001010010000000000000000000000100011100100 -
1%
#1380
0%
b100100000100 (
b100100000100 +
#1385
b0 ,
1"
0!
b10 0
b10001110010000000000000000000000100011110100 $
b10001110010000000000000000000000100011110100 -
1%
#1390
0%
b100100010100 (
b100100010100 +
#1395
1!
0"
b0 0
1%
#1400
0%
b100100100100 (
b100100100100 +
#1405
b1 ,
b1 0
b10001110010000000000000000000000100100100100 /
1%
#1410
0%
b100100110100 (
b100100110100 +
#1415
b10 ,
b10010010010000000000000000000000100100110100 /
b10001110010000000000000000000000100100100100 $
b10001110010000000000000000000000100100100100 -
1%
#1420
0%
b100101000100 (
b100101000100 +
#1425
b0 ,
1"
0!
b10 0
b10010010010000000000000000000000100100110100 $
b10010010010000000000000000000000100100110100 -
1%
#1430
0%
b100101010100 (
b100101010100 +
#1435
1!
0"
b0 0
1%
#1440
0%
b100101100100 (
b100101100100 +
#1445
b1 ,
b1 0
b10010010010000000000000000000000100101100100 /
1%
#1450
0%
b100101110100 (
b100101110100 +
#1455
b10 ,
b10010110010000000000000000000000100101110100 /
b10010010010000000000000000000000100101100100 $
b10010010010000000000000000000000100101100100 -
1%
#1460
0%
b100110000100 (
b100110000100 +
#1465
b0 ,
1"
0!
b10 0
b10010110010000000000000000000000100101110100 $
b10010110010000000000000000000000100101110100 -
1%
#1470
0%
b100110010100 (
b100110010100 +
#1475
1!
0"
b0 0
1%
#1480
0%
b100110100100 (
b100110100100 +
#1485
b1 ,
b1 0
b10010110010000000000000000000000100110100100 /
1%
#1490
0%
b100110110100 (
b100110110100 +
#1495
b10 ,
b10011010010000000000000000000000100110110100 /
b10010110010000000000000000000000100110100100 $
b10010110010000000000000000000000100110100100 -
1%
#1500
0%
b100111000100 (
b100111000100 +
#1505
b0 ,
1"
0!
b10 0
b10011010010000000000000000000000100110110100 $
b10011010010000000000000000000000100110110100 -
1%
#1510
0%
b100111010100 (
b100111010100 +
#1515
1!
0"
b0 0
1%
#1520
0%
b100111100100 (
b100111100100 +
#1525
b1 ,
b1 0
b10011010010000000000000000000000100111100100 /
1%
#1530
0%
b100111110100 (
b100111110100 +
#1535
b10 ,
b10011110010000000000000000000000100111110100 /
b10011010010000000000000000000000100111100100 $
b10011010010000000000000000000000100111100100 -
1%
#1540
0%
b101000000100 (
b101000000100 +
#1545
b0 ,
1"
0!
b10 0
b10011110010000000000000000000000100111110100 $
b10011110010000000000000000000000100111110100 -
1%
#1550
0%
b101000010100 (
b101000010100 +
#1555
1!
0"
b0 0
1%
#1560
0%
b101000100100 (
b101000100100 +
#1565
b1 ,
b1 0
b10011110010000000000000000000000101000100100 /
1%
#1570
0%
b101000110100 (
b101000110100 +
#1575
b10 ,
b10100010010000000000000000000000101000110100 /
b10011110010000000000000000000000101000100100 $
b10011110010000000000000000000000101000100100 -
1%
#1580
0%
b101001000100 (
b101001000100 +
#1585
b0 ,
1"
0!
b10 0
b10100010010000000000000000000000101000110100 $
b10100010010000000000000000000000101000110100 -
1%
#1590
0%
b101001010100 (
b101001010100 +
#1595
1!
0"
b0 0
1%
#1600
0%
b101001100100 (
b101001100100 +
#1605
b1 ,
b1 0
b10100010010000000000000000000000101001100100 /
1%
#1610
0%
b101001110100 (
b101001110100 +
#1615
b10 ,
b10100110010000000000000000000000101001110100 /
b10100010010000000000000000000000101001100100 $
b10100010010000000000000000000000101001100100 -
1%
#1620
0%
b101010000100 (
b101010000100 +
#1625
b0 ,
1"
0!
b10 0
b10100110010000000000000000000000101001110100 $
b10100110010000000000000000000000101001110100 -
1%
#1630
0%
b101010010100 (
b101010010100 +
#1635
1!
0"
b0 0
1%
#1640
0%
b101010100100 (
b101010100100 +
#1645
b1 ,
b1 0
b10100110010000000000000000000000101010100100 /
1%
#1650
0%
b101010110100 (
b101010110100 +
#1655
b10 ,
b10101010010000000000000000000000101010110100 /
b10100110010000000000000000000000101010100100 $
b10100110010000000000000000000000101010100100 -
1%
#1660
0%
b101011000100 (
b101011000100 +
#1665
b0 ,
1"
0!
b10 0
b10101010010000000000000000000000101010110100 $
b10101010010000000000000000000000101010110100 -
1%
#1670
0%
b101011010100 (
b101011010100 +
#1675
1!
0"
b0 0
1%
#1680
0%
b101011100100 (
b101011100100 +
#1685
b1 ,
b1 0
b10101010010000000000000000000000101011100100 /
1%
#1690
0%
b101011110100 (
b101011110100 +
#1695
b10 ,
b10101110010000000000000000000000101011110100 /
b10101010010000000000000000000000101011100100 $
b10101010010000000000000000000000101011100100 -
1%
#1700
0%
b101100000100 (
b101100000100 +
#1705
b0 ,
1"
0!
b10 0
b10101110010000000000000000000000101011110100 $
b10101110010000000000000000000000101011110100 -
1%
#1710
0%
b101100010100 (
b101100010100 +
#1715
1!
0"
b0 0
1%
#1720
0%
b101100100100 (
b101100100100 +
#1725
b1 ,
b1 0
b10101110010000000000000000000000101100100100 /
1%
#1730
0%
b101100110100 (
b101100110100 +
#1735
b10 ,
b10110010010000000000000000000000101100110100 /
b10101110010000000000000000000000101100100100 $
b10101110010000000000000000000000101100100100 -
1%
#1740
0%
b101101000100 (
b101101000100 +
#1745
b0 ,
1"
0!
b10 0
b10110010010000000000000000000000101100110100 $
b10110010010000000000000000000000101100110100 -
1%
#1750
0%
b101101010100 (
b101101010100 +
#1755
1!
0"
b0 0
1%
#1760
0%
b101101100100 (
b101101100100 +
#1765
b1 ,
b1 0
b10110010010000000000000000000000101101100100 /
1%
#1770
0%
b101101110100 (
b101101110100 +
#1775
b10 ,
b10110110010000000000000000000000101101110100 /
b10110010010000000000000000000000101101100100 $
b10110010010000000000000000000000101101100100 -
1%
#1780
0%
b101110000100 (
b101110000100 +
#1785
b0 ,
1"
0!
b10 0
b10110110010000000000000000000000101101110100 $
b10110110010000000000000000000000101101110100 -
1%
#1790
0%
b101110010100 (
b101110010100 +
#1795
1!
0"
b0 0
1%
#1800
0%
b101110100100 (
b101110100100 +
#1805
b1 ,
b1 0
b10110110010000000000000000000000101110100100 /
1%
#1810
0%
b101110110100 (
b101110110100 +
#1815
b10 ,
b10111010010000000000000000000000101110110100 /
b10110110010000000000000000000000101110100100 $
b10110110010000000000000000000000101110100100 -
1%
#1820
0%
b101111000100 (
b101111000100 +
#1825
b0 ,
1"
0!
b10 0
b10111010010000000000000000000000101110110100 $
b10111010010000000000000000000000101110110100 -
1%
#1830
0%
b101111010100 (
b101111010100 +
#1835
1!
0"
b0 0
1%
#1840
0%
b101111100100 (
b101111100100 +
#1845
b1 ,
b1 0
b10111010010000000000000000000000101111100100 /
1%
#1850
0%
b101111110100 (
b101111110100 +
