Downsizer.sv
module axis_dwidth_downsizer #(
  parameter WIDTH      = 32, // output width
  parameter NUM_REG    =  2 // Scale factor
)(
    input  logic aclk,                    // input wire aclk
    input  logic aresetn,              // input wire aresetn
    input  logic s_axis_tvalid,  // input wire s_axis_tvalid
    output logic s_axis_tready,  // output wire s_axis_tready
    input  logic [WIDTH*NUM_REG-1:0] s_axis_tdata,    // input wire [63 : 0] s_axis_tdata
    input  logic s_axis_tlast,   

    output logic m_axis_tvalid,  // output wire m_axis_tvalid
    input  logic m_axis_tready,  // input wire m_axis_tready
    output [WIDTH-1:0] m_axis_tdata,    // output wire [31 : 0] m_axis_tdata
    output m_axis_tlast
);
  // Define the states as enum
    localparam READY = 0;
    localparam SHIFT = 1;
    localparam LAST = 2;

  logic [NUM_REG*WIDTH - 1:0] s_reg;
  logic [32:0] cnt;
  // Define state register and next state variables
  logic [1:0] state_reg;
  logic m_axis_tlast_local;
  assign m_axis_tdata = s_reg[NUM_REG*WIDTH - 1:(NUM_REG-1)*WIDTH];
  assign m_axis_tlast = (cnt == NUM_REG - 1) & m_axis_tlast_local;
  always @(posedge aclk) begin
    
    if (aresetn == 0) begin
      state_reg       <= READY;
      cnt             <=  0;
      s_axis_tready   <=  1;
      m_axis_tvalid   <=  0;
      m_axis_tlast_local <= 0;
      s_reg           <= '0;
    end else begin
      if (s_axis_tlast == 1) m_axis_tlast_local <= 1;
      // State transitions and outputs
      case (state_reg)
        READY:
          begin
            cnt <=  0;
            if (s_axis_tvalid == 1) begin
              s_reg       <= s_axis_tdata;
              state_reg   <= SHIFT;
              s_axis_tready <= 0;
              m_axis_tvalid <= 1;
            end
          end
        SHIFT:
          begin
            if (cnt < NUM_REG - 1  & m_axis_tready == 1) begin
                cnt   <= cnt + 1;
                s_reg <= s_reg << WIDTH;
            end else if (cnt < NUM_REG - 1 & m_axis_tready == 0) 
                state_reg <= SHIFT;
            else begin
                state_reg <= LAST;
	              m_axis_tvalid <= 0;
                m_axis_tlast_local <= 0;
	          end
          end
        LAST:
          begin
            if (m_axis_tready == 1) begin
                state_reg     <= READY;
                s_axis_tready <= 1;	
	        end
          end
        
        // Define transitions for other states
      endcase
    end
  end
endmodule

Downsizer_tb.sv
module test;
  localparam WIDTH = 32;
  localparam NUM_REG=2;

  /* Make a reset that pulses once. */
  reg reset = 1;
  initial begin
     # 5 reset = 0;
     # 50 reset = 1;
     # 300 $stop;
  end

  /* Make a regular pulsing clock. */
  reg clk = 0;
  always #5 clk = !clk;

  reg s_axis_tvalid = 0;
  reg [WIDTH*NUM_REG-1:0] s_axis_tdata = (1 << WIDTH) + 100;
  reg s_axis_tlast = 0;
  reg m_axis_tready = 1;
  initial begin
    #80 s_axis_tvalid = 1;
    #120 s_axis_tlast = 1;
    #10 s_axis_tlast = 0;
  end
  always #20 s_axis_tdata = s_axis_tdata + (1 << WIDTH) + 16;

  wire s_axis_tready;
  wire m_axis_tvalid;
  wire [WIDTH-1:0] m_axis_tdata;
  wire m_axis_tlast;
  axis_dwidth_downsizer downsizer (.aclk(clk),                    // input wire aclk
    .aresetn(reset),              // input wire aresetn
    .s_axis_tvalid(s_axis_tvalid),  // input wire s_axis_tvalid
    .s_axis_tready(s_axis_tready),  // output wire s_axis_tready
    .s_axis_tdata(s_axis_tdata),    // input wire [64 : 0] s_axis_tdata
    .s_axis_tlast(s_axis_tlast),   

    .m_axis_tvalid(m_axis_tvalid),  // output wire m_axis_tvalid
    .m_axis_tready(m_axis_tready),  // input wire m_axis_tready
    .m_axis_tdata(m_axis_tdata),    // output wire [32 : 0] m_axis_tdata
    .m_axis_tlast(m_axis_tlast));

  initial begin
    $dumpfile("test_downsizer.vcd");
    $dumpvars(0,test);
    
    // $monitor("At time %t, value = %h (%0d)",
    //           $time, value, value);
  end
endmodule // test

test_downsizer.vcd
$date
	Wed May 24 17:27:20 2023
$end
$version
	Icarus Verilog
$end
$timescale
	1s
$end
$scope module test $end
$var wire 1 ! s_axis_tready $end
$var wire 1 " m_axis_tvalid $end
$var wire 1 # m_axis_tlast $end
$var wire 32 $ m_axis_tdata [31:0] $end
$var reg 1 % clk $end
$var reg 1 & m_axis_tready $end
$var reg 1 ' reset $end
$var reg 64 ( s_axis_tdata [63:0] $end
$var reg 1 ) s_axis_tlast $end
$var reg 1 * s_axis_tvalid $end
$scope module downsizer $end
$var wire 1 % aclk $end
$var wire 1 ' aresetn $end
$var wire 1 # m_axis_tlast $end
$var wire 1 & m_axis_tready $end
$var wire 64 + s_axis_tdata [63:0] $end
$var wire 1 ) s_axis_tlast $end
$var wire 1 * s_axis_tvalid $end
$var wire 32 , m_axis_tdata [31:0] $end
$var reg 33 - cnt [32:0] $end
$var reg 1 . m_axis_tlast_local $end
$var reg 1 " m_axis_tvalid $end
$var reg 1 ! s_axis_tready $end
$var reg 64 / s_reg [63:0] $end
$var reg 2 0 state_reg [1:0] $end
$upscope $end
$upscope $end
$enddefinitions $end
#0
$dumpvars
bx 0
bx /
x.
bx -
bx ,
b100000000000000000000000001100100 +
0*
0)
b100000000000000000000000001100100 (
1'
1&
0%
bx $
x#
x"
x!
$end
#5
b0 $
b0 ,
0#
b0 /
0.
0"
1!
b0 -
b0 0
1%
0'
#10
0%
#15
1%
#20
0%
b1000000000000000000000000001110100 (
b1000000000000000000000000001110100 +
#25
1%
#30
0%
#35
1%
#40
0%
b1100000000000000000000000010000100 (
b1100000000000000000000000010000100 +
#45
1%
#50
0%
#55
1%
1'
#60
0%
b10000000000000000000000000010010100 (
b10000000000000000000000000010010100 +
#65
1%
#70
0%
#75
1%
#80
0%
b10100000000000000000000000010100100 (
b10100000000000000000000000010100100 +
1*
#85
b101 $
b101 ,
1"
0!
b1 0
b10100000000000000000000000010100100 /
1%
#90
0%
#95
b10100100 $
b10100100 ,
b1010010000000000000000000000000000000000 /
b1 -
1%
#100
0%
b11000000000000000000000000010110100 (
b11000000000000000000000000010110100 +
#105
0"
b10 0
1%
#110
0%
#115
1!
b0 0
1%
#120
0%
b11100000000000000000000000011000100 (
b11100000000000000000000000011000100 +
#125
b111 $
b111 ,
1"
0!
b1 0
b11100000000000000000000000011000100 /
b0 -
1%
#130
0%
#135
b11000100 $
b11000100 ,
b1100010000000000000000000000000000000000 /
b1 -
1%
#140
0%
b100000000000000000000000000011010100 (
b100000000000000000000000000011010100 +
#145
0"
b10 0
1%
#150
0%
#155
1!
b0 0
1%
#160
0%
b100100000000000000000000000011100100 (
b100100000000000000000000000011100100 +
#165
b1001 $
b1001 ,
1"
0!
b1 0
b100100000000000000000000000011100100 /
b0 -
1%
#170
0%
#175
b11100100 $
b11100100 ,
b1110010000000000000000000000000000000000 /
b1 -
1%
#180
0%
b101000000000000000000000000011110100 (
b101000000000000000000000000011110100 +
#185
0"
b10 0
1%
#190
0%
#195
1!
b0 0
1%
#200
0%
b101100000000000000000000000100000100 (
b101100000000000000000000000100000100 +
1)
#205
b1011 $
b1011 ,
1"
0!
b1 0
b101100000000000000000000000100000100 /
b0 -
1.
1%
#210
0%
0)
#215
b100000100 $
b100000100 ,
1#
b10000010000000000000000000000000000000000 /
b1 -
1%
#220
0%
b110000000000000000000000000100010100 (
b110000000000000000000000000100010100 +
#225
0#
0.
0"
b10 0
1%
#230
0%
#235
1!
b0 0
1%
#240
0%
b110100000000000000000000000100100100 (
b110100000000000000000000000100100100 +
#245
b1101 $
b1101 ,
1"
0!
b1 0
b110100000000000000000000000100100100 /
b0 -
1%
#250
0%
#255
b100100100 $
b100100100 ,
b10010010000000000000000000000000000000000 /
b1 -
1%
#260
0%
b111000000000000000000000000100110100 (
b111000000000000000000000000100110100 +
#265
0"
b10 0
1%
#270
0%
#275
1!
b0 0
1%
#280
0%
b111100000000000000000000000101000100 (
b111100000000000000000000000101000100 +
#285
b1111 $
b1111 ,
1"
0!
b1 0
b111100000000000000000000000101000100 /
b0 -
1%
#290
0%
#295
b101000100 $
b101000100 ,
b10100010000000000000000000000000000000000 /
b1 -
1%
#300
0%
b1000000000000000000000000000101010100 (
b1000000000000000000000000000101010100 +
#305
0"
b10 0
1%
#310
0%
#315
1!
b0 0
1%
#320
0%
b1000100000000000000000000000101100100 (
b1000100000000000000000000000101100100 +
#325
b10001 $
b10001 ,
1"
0!
b1 0
b1000100000000000000000000000101100100 /
b0 -
1%
#330
0%
#335
b101100100 $
b101100100 ,
b10110010000000000000000000000000000000000 /
b1 -
1%
#340
0%
b1001000000000000000000000000101110100 (
b1001000000000000000000000000101110100 +
#345
0"
b10 0
1%
