Upsizer.sv
module my_axis_dwidth_upsize #(
  parameter WIDTH      = 32, // input width
  parameter NUM_REG    =  2 // Scale factor
)(
    input  logic aclk,                    // input wire aclk
    input  logic aresetn,              // input wire aresetn
    input  logic s_axis_tvalid,  // input wire s_axis_tvalid
    output logic s_axis_tready,  // output wire s_axis_tready
    input  logic [WIDTH-1:0] s_axis_tdata,    // input wire [31 : 0] s_axis_tdata
    input  logic s_axis_tlast,   

    output logic m_axis_tvalid,  // output wire m_axis_tvalid
    input  logic m_axis_tready,  // input wire m_axis_tready
    output logic [WIDTH*NUM_REG-1:0] m_axis_tdata,    // output wire [63 : 0] m_axis_tdata
    output logic m_axis_tlast
);
  // Define the states as enum
    localparam READY = 0;
    localparam LOAD = 1;
    localparam WRTARRAY = 2;

  logic [NUM_REG*WIDTH - 1:0] s_reg;
  logic [63:0] cnt;
  // Define state register and next state variables
  logic [1:0] state_reg;
//   logic [1:0] next_state;
  always @(posedge aclk) begin
    if (aresetn == 0) begin
      state_reg       <= READY;
      cnt             <=  0;
      s_axis_tready   <=  1;
      m_axis_tvalid   <=  0;
      s_reg           <= '0;
    end else begin
      m_axis_tdata    <= s_reg;
      // State transitions and outputs
      case (state_reg)
        READY:
          begin
            cnt <=  0;
            if (s_axis_tvalid == 1) begin
              s_reg[WIDTH-1:0] <= s_axis_tdata;
              state_reg   <= LOAD;
              cnt           <= cnt + 1;	
            end
          end
        LOAD:
          begin
            if (cnt < NUM_REG  & s_axis_tvalid == 1) begin
              s_reg <= (s_reg << WIDTH) | s_axis_tdata;
              cnt            <= cnt + 1;
              state_reg      <= LOAD;
            end else if (cnt < NUM_REG & s_axis_tvalid == 0) 
              state_reg <= LOAD;
            else begin
              state_reg       <= WRTARRAY;
              s_axis_tready   <= 0;
              m_axis_tvalid   <= 1;
              cnt <= 0;
            end
          end
        WRTARRAY:
          begin
            if (m_axis_tready == 1) begin
              state_reg       <= READY;
              m_axis_tvalid <= 0;
              s_axis_tready   <= 1;
            end
          end
        
        // Define transitions for other states
      endcase
    end
  end
endmodule

Upsizer_tb.sv
module test;
  localparam WIDTH = 32;
  localparam NUM_REG=2;

  /* Make a reset that pulses once. */
  reg reset = 1;
  initial begin
     # 5 reset = 0;
     # 50 reset = 1;
     # 1000 $stop;
  end

  /* Make a regular pulsing clock. */
  reg clk = 0;
  always #5 clk = !clk;

  reg s_axis_tvalid = 0;
  reg [WIDTH-1:0] s_axis_tdata = 100;
  reg s_axis_tlast = 0;
  reg m_axis_tready = 1;
  initial begin
    #100 s_axis_tvalid = 1;
  end
  always #10 s_axis_tdata = s_axis_tdata + 16;

  wire s_axis_tready;
  wire m_axis_tvalid;
  wire [WIDTH*NUM_REG-1:0] m_axis_tdata;
  wire m_axis_tlast;
  my_axis_dwidth_upsize upsizer (.aclk(clk),                    // input wire aclk
    .aresetn(reset),              // input wire aresetn
    .s_axis_tvalid(s_axis_tvalid),  // input wire s_axis_tvalid
    .s_axis_tready(s_axis_tready),  // output wire s_axis_tready
    .s_axis_tdata(s_axis_tdata),    // input wire [31 : 0] s_axis_tdata
    .s_axis_tlast(s_axis_tlast),   

    .m_axis_tvalid(m_axis_tvalid),  // output wire m_axis_tvalid
    .m_axis_tready(m_axis_tready),  // input wire m_axis_tready
    .m_axis_tdata(m_axis_tdata),    // output wire [63 : 0] m_axis_tdata
    .m_axis_tlast(m_axis_tlast));

  initial begin
    $dumpfile("test.vcd");
    $dumpvars(0,test);
    
    // $monitor("At time %t, value = %h (%0d)",
    //           $time, value, value);
  end
endmodule // test

test.vcd
$date
	Wed May 24 10:45:32 2023
$end
$version
	Icarus Verilog
$end
$timescale
	1s
$end
$scope module test $end
$var wire 1 ! s_axis_tready $end
$var wire 1 " m_axis_tvalid $end
$var wire 1 # m_axis_tlast $end
$var wire 64 $ m_axis_tdata [63:0] $end
$var reg 1 % clk $end
$var reg 1 & m_axis_tready $end
$var reg 1 ' reset $end
$var reg 32 ( s_axis_tdata [31:0] $end
$var reg 1 ) s_axis_tlast $end
$var reg 1 * s_axis_tvalid $end
$scope module upsizer $end
$var wire 1 % aclk $end
$var wire 1 ' aresetn $end
$var wire 1 & m_axis_tready $end
$var wire 32 + s_axis_tdata [31:0] $end
$var wire 1 ) s_axis_tlast $end
$var wire 1 * s_axis_tvalid $end
$var reg 64 , cnt [63:0] $end
$var reg 64 - m_axis_tdata [63:0] $end
$var reg 1 # m_axis_tlast $end
$var reg 1 " m_axis_tvalid $end
$var reg 1 ! s_axis_tready $end
$var reg 64 . s_reg [63:0] $end
$var reg 2 / state_reg [1:0] $end
$upscope $end
$upscope $end
$enddefinitions $end
#0
$dumpvars
bx /
bx .
bx -
bx ,
b1100100 +
0*
0)
b1100100 (
1'
1&
0%
bx $
x#
x"
x!
$end
#5
b0 .
0"
1!
b0 ,
b0 /
1%
0'
#10
0%
b1110100 (
b1110100 +
#15
1%
#20
0%
b10000100 (
b10000100 +
#25
1%
#30
0%
b10010100 (
b10010100 +
#35
1%
#40
0%
b10100100 (
b10100100 +
#45
1%
#50
0%
b10110100 (
b10110100 +
#55
b0 $
b0 -
1%
1'
#60
0%
b11000100 (
b11000100 +
#65
1%
#70
0%
b11010100 (
b11010100 +
#75
1%
#80
0%
b11100100 (
b11100100 +
#85
1%
#90
0%
b11110100 (
b11110100 +
#95
1%
#100
0%
b100000100 (
b100000100 +
1*
#105
b1 ,
b1 /
b100000100 .
1%
#110
0%
b100010100 (
b100010100 +
#115
b10 ,
b10000010000000000000000000000000100010100 .
b100000100 $
b100000100 -
1%
#120
0%
b100100100 (
b100100100 +
#125
b0 ,
1"
0!
b10 /
b10000010000000000000000000000000100010100 $
b10000010000000000000000000000000100010100 -
1%
#130
0%
b100110100 (
b100110100 +
#135
1!
0"
b0 /
1%
#140
0%
b101000100 (
b101000100 +
#145
b1 ,
b1 /
b10000010000000000000000000000000101000100 .
1%
#150
0%
b101010100 (
b101010100 +
#155
b10 ,
b10100010000000000000000000000000101010100 .
b10000010000000000000000000000000101000100 $
b10000010000000000000000000000000101000100 -
1%
#160
0%
b101100100 (
b101100100 +
#165
b0 ,
1"
0!
b10 /
b10100010000000000000000000000000101010100 $
b10100010000000000000000000000000101010100 -
1%
#170
0%
b101110100 (
b101110100 +
#175
1!
0"
b0 /
1%
#180
0%
b110000100 (
b110000100 +
#185
b1 ,
b1 /
b10100010000000000000000000000000110000100 .
1%
#190
0%
b110010100 (
b110010100 +
#195
b10 ,
b11000010000000000000000000000000110010100 .
b10100010000000000000000000000000110000100 $
b10100010000000000000000000000000110000100 -
1%
#200
0%
b110100100 (
b110100100 +
#205
b0 ,
1"
0!
b10 /
b11000010000000000000000000000000110010100 $
b11000010000000000000000000000000110010100 -
1%
#210
0%
b110110100 (
b110110100 +
#215
1!
0"
b0 /
1%
#220
0%
b111000100 (
b111000100 +
#225
b1 ,
b1 /
b11000010000000000000000000000000111000100 .
1%
#230
0%
b111010100 (
b111010100 +
#235
b10 ,
b11100010000000000000000000000000111010100 .
b11000010000000000000000000000000111000100 $
b11000010000000000000000000000000111000100 -
1%
#240
0%
b111100100 (
b111100100 +
#245
b0 ,
1"
0!
b10 /
b11100010000000000000000000000000111010100 $
b11100010000000000000000000000000111010100 -
1%
#250
0%
b111110100 (
b111110100 +
#255
1!
0"
b0 /
1%
#260
0%
b1000000100 (
b1000000100 +
#265
b1 ,
b1 /
b11100010000000000000000000000001000000100 .
1%
#270
0%
b1000010100 (
b1000010100 +
#275
b10 ,
b100000010000000000000000000000001000010100 .
b11100010000000000000000000000001000000100 $
b11100010000000000000000000000001000000100 -
1%
#280
0%
b1000100100 (
b1000100100 +
#285
b0 ,
1"
0!
b10 /
b100000010000000000000000000000001000010100 $
b100000010000000000000000000000001000010100 -
1%
#290
0%
b1000110100 (
b1000110100 +
#295
1!
0"
b0 /
1%
#300
0%
b1001000100 (
b1001000100 +
#305
b1 ,
b1 /
b100000010000000000000000000000001001000100 .
1%
#310
0%
b1001010100 (
b1001010100 +
#315
b10 ,
b100100010000000000000000000000001001010100 .
b100000010000000000000000000000001001000100 $
b100000010000000000000000000000001001000100 -
1%
#320
0%
b1001100100 (
b1001100100 +
#325
b0 ,
1"
0!
b10 /
b100100010000000000000000000000001001010100 $
b100100010000000000000000000000001001010100 -
1%
#330
0%
b1001110100 (
b1001110100 +
#335
1!
0"
b0 /
1%
#340
0%
b1010000100 (
b1010000100 +
#345
b1 ,
b1 /
b100100010000000000000000000000001010000100 .
1%
#350
0%
b1010010100 (
b1010010100 +
#355
b10 ,
b101000010000000000000000000000001010010100 .
b100100010000000000000000000000001010000100 $
b100100010000000000000000000000001010000100 -
1%
#360
0%
b1010100100 (
b1010100100 +
#365
b0 ,
1"
0!
b10 /
b101000010000000000000000000000001010010100 $
b101000010000000000000000000000001010010100 -
1%
#370
0%
b1010110100 (
b1010110100 +
#375
1!
0"
b0 /
1%
#380
0%
b1011000100 (
b1011000100 +
#385
b1 ,
b1 /
b101000010000000000000000000000001011000100 .
1%
#390
0%
b1011010100 (
b1011010100 +
#395
b10 ,
b101100010000000000000000000000001011010100 .
b101000010000000000000000000000001011000100 $
b101000010000000000000000000000001011000100 -
1%
#400
0%
b1011100100 (
b1011100100 +
#405
b0 ,
1"
0!
b10 /
b101100010000000000000000000000001011010100 $
b101100010000000000000000000000001011010100 -
1%
#410
0%
b1011110100 (
b1011110100 +
#415
1!
0"
b0 /
1%
#420
0%
b1100000100 (
b1100000100 +
#425
b1 ,
b1 /
b101100010000000000000000000000001100000100 .
1%
#430
0%
b1100010100 (
b1100010100 +
#435
b10 ,
b110000010000000000000000000000001100010100 .
b101100010000000000000000000000001100000100 $
b101100010000000000000000000000001100000100 -
1%
#440
0%
b1100100100 (
b1100100100 +
#445
b0 ,
1"
0!
b10 /
b110000010000000000000000000000001100010100 $
b110000010000000000000000000000001100010100 -
1%
#450
0%
b1100110100 (
b1100110100 +
#455
1!
0"
b0 /
1%
#460
0%
b1101000100 (
b1101000100 +
#465
b1 ,
b1 /
b110000010000000000000000000000001101000100 .
1%
#470
0%
b1101010100 (
b1101010100 +
#475
b10 ,
b110100010000000000000000000000001101010100 .
b110000010000000000000000000000001101000100 $
b110000010000000000000000000000001101000100 -
1%
#480
0%
b1101100100 (
b1101100100 +
#485
b0 ,
1"
0!
b10 /
b110100010000000000000000000000001101010100 $
b110100010000000000000000000000001101010100 -
1%
#490
0%
b1101110100 (
b1101110100 +
#495
1!
0"
b0 /
1%
#500
0%
b1110000100 (
b1110000100 +
#505
b1 ,
b1 /
b110100010000000000000000000000001110000100 .
1%
#510
0%
b1110010100 (
b1110010100 +
#515
b10 ,
b111000010000000000000000000000001110010100 .
b110100010000000000000000000000001110000100 $
b110100010000000000000000000000001110000100 -
1%
#520
0%
b1110100100 (
b1110100100 +
#525
b0 ,
1"
0!
b10 /
b111000010000000000000000000000001110010100 $
b111000010000000000000000000000001110010100 -
1%
#530
0%
b1110110100 (
b1110110100 +
#535
1!
0"
b0 /
1%
#540
0%
b1111000100 (
b1111000100 +
#545
b1 ,
b1 /
b111000010000000000000000000000001111000100 .
1%
#550
0%
b1111010100 (
b1111010100 +
#555
b10 ,
b111100010000000000000000000000001111010100 .
b111000010000000000000000000000001111000100 $
b111000010000000000000000000000001111000100 -
1%
#560
0%
b1111100100 (
b1111100100 +
#565
b0 ,
1"
0!
b10 /
b111100010000000000000000000000001111010100 $
b111100010000000000000000000000001111010100 -
1%
#570
0%
b1111110100 (
b1111110100 +
#575
1!
0"
b0 /
1%
#580
0%
b10000000100 (
b10000000100 +
#585
b1 ,
b1 /
b111100010000000000000000000000010000000100 .
1%
#590
0%
b10000010100 (
b10000010100 +
#595
b10 ,
b1000000010000000000000000000000010000010100 .
b111100010000000000000000000000010000000100 $
b111100010000000000000000000000010000000100 -
1%
#600
0%
b10000100100 (
b10000100100 +
#605
b0 ,
1"
0!
b10 /
b1000000010000000000000000000000010000010100 $
b1000000010000000000000000000000010000010100 -
1%
#610
0%
b10000110100 (
b10000110100 +
#615
1!
0"
b0 /
1%
#620
0%
b10001000100 (
b10001000100 +
#625
b1 ,
b1 /
b1000000010000000000000000000000010001000100 .
1%
#630
0%
b10001010100 (
b10001010100 +
#635
b10 ,
b1000100010000000000000000000000010001010100 .
b1000000010000000000000000000000010001000100 $
b1000000010000000000000000000000010001000100 -
1%
#640
0%
b10001100100 (
b10001100100 +
#645
b0 ,
1"
0!
b10 /
b1000100010000000000000000000000010001010100 $
b1000100010000000000000000000000010001010100 -
1%
#650
0%
b10001110100 (
b10001110100 +
#655
1!
0"
b0 /
1%
#660
0%
b10010000100 (
b10010000100 +
#665
b1 ,
b1 /
b1000100010000000000000000000000010010000100 .
1%
#670
0%
b10010010100 (
b10010010100 +
#675
b10 ,
b1001000010000000000000000000000010010010100 .
b1000100010000000000000000000000010010000100 $
b1000100010000000000000000000000010010000100 -
1%
#680
0%
b10010100100 (
b10010100100 +
#685
b0 ,
1"
0!
b10 /
b1001000010000000000000000000000010010010100 $
b1001000010000000000000000000000010010010100 -
1%
#690
0%
b10010110100 (
b10010110100 +
#695
1!
0"
b0 /
1%
#700
0%
b10011000100 (
b10011000100 +
#705
b1 ,
b1 /
b1001000010000000000000000000000010011000100 .
1%
#710
0%
b10011010100 (
b10011010100 +
#715
b10 ,
b1001100010000000000000000000000010011010100 .
b1001000010000000000000000000000010011000100 $
b1001000010000000000000000000000010011000100 -
1%
#720
0%
b10011100100 (
b10011100100 +
#725
b0 ,
1"
0!
b10 /
b1001100010000000000000000000000010011010100 $
b1001100010000000000000000000000010011010100 -
1%
#730
0%
b10011110100 (
b10011110100 +
#735
1!
0"
b0 /
1%
#740
0%
b10100000100 (
b10100000100 +
#745
b1 ,
b1 /
b1001100010000000000000000000000010100000100 .
1%
#750
0%
b10100010100 (
b10100010100 +
#755
b10 ,
b1010000010000000000000000000000010100010100 .
b1001100010000000000000000000000010100000100 $
b1001100010000000000000000000000010100000100 -
1%
#760
0%
b10100100100 (
b10100100100 +
#765
b0 ,
1"
0!
b10 /
b1010000010000000000000000000000010100010100 $
b1010000010000000000000000000000010100010100 -
1%
#770
0%
b10100110100 (
b10100110100 +
#775
1!
0"
b0 /
1%
#780
0%
b10101000100 (
b10101000100 +
#785
b1 ,
b1 /
b1010000010000000000000000000000010101000100 .
1%
#790
0%
b10101010100 (
b10101010100 +
#795
b10 ,
b1010100010000000000000000000000010101010100 .
b1010000010000000000000000000000010101000100 $
b1010000010000000000000000000000010101000100 -
1%
#800
0%
b10101100100 (
b10101100100 +
#805
b0 ,
1"
0!
b10 /
b1010100010000000000000000000000010101010100 $
b1010100010000000000000000000000010101010100 -
1%
#810
0%
b10101110100 (
b10101110100 +
#815
1!
0"
b0 /
1%
#820
0%
b10110000100 (
b10110000100 +
#825
b1 ,
b1 /
b1010100010000000000000000000000010110000100 .
1%
#830
0%
b10110010100 (
b10110010100 +
#835
b10 ,
b1011000010000000000000000000000010110010100 .
b1010100010000000000000000000000010110000100 $
b1010100010000000000000000000000010110000100 -
1%
#840
0%
b10110100100 (
b10110100100 +
#845
b0 ,
1"
0!
b10 /
b1011000010000000000000000000000010110010100 $
b1011000010000000000000000000000010110010100 -
1%
#850
0%
b10110110100 (
b10110110100 +
#855
1!
0"
b0 /
1%
#860
0%
b10111000100 (
b10111000100 +
#865
b1 ,
b1 /
b1011000010000000000000000000000010111000100 .
1%
#870
0%
b10111010100 (
b10111010100 +
#875
b10 ,
b1011100010000000000000000000000010111010100 .
b1011000010000000000000000000000010111000100 $
b1011000010000000000000000000000010111000100 -
1%
#880
0%
b10111100100 (
b10111100100 +
#885
b0 ,
1"
0!
b10 /
b1011100010000000000000000000000010111010100 $
b1011100010000000000000000000000010111010100 -
1%
#890
0%
b10111110100 (
b10111110100 +
#895
1!
0"
b0 /
1%
#900
0%
b11000000100 (
b11000000100 +
#905
b1 ,
b1 /
b1011100010000000000000000000000011000000100 .
1%
#910
0%
b11000010100 (
b11000010100 +
#915
b10 ,
b1100000010000000000000000000000011000010100 .
b1011100010000000000000000000000011000000100 $
b1011100010000000000000000000000011000000100 -
1%
#920
0%
b11000100100 (
b11000100100 +
#925
b0 ,
1"
0!
b10 /
b1100000010000000000000000000000011000010100 $
b1100000010000000000000000000000011000010100 -
1%
#930
0%
b11000110100 (
b11000110100 +
#935
1!
0"
b0 /
1%
#940
0%
b11001000100 (
b11001000100 +
#945
b1 ,
b1 /
b1100000010000000000000000000000011001000100 .
1%
#950
0%
b11001010100 (
b11001010100 +
#955
b10 ,
b1100100010000000000000000000000011001010100 .
b1100000010000000000000000000000011001000100 $
b1100000010000000000000000000000011001000100 -
1%
#960
0%
b11001100100 (
b11001100100 +
#965
b0 ,
1"
0!
b10 /
b1100100010000000000000000000000011001010100 $
b1100100010000000000000000000000011001010100 -
1%
#970
0%
b11001110100 (
b11001110100 +
#975
1!
0"
b0 /
1%
#980
0%
b11010000100 (
b11010000100 +
#985
b1 ,
b1 /
b1100100010000000000000000000000011010000100 .
1%
#990
0%
b11010010100 (
b11010010100 +
#995
b10 ,
b1101000010000000000000000000000011010010100 .
b1100100010000000000000000000000011010000100 $
b1100100010000000000000000000000011010000100 -
1%
#1000
0%
b11010100100 (
b11010100100 +
#1005
b0 ,
1"
0!
b10 /
b1101000010000000000000000000000011010010100 $
b1101000010000000000000000000000011010010100 -
1%
#1010
0%
b11010110100 (
b11010110100 +
#1015
1!
0"
b0 /
1%
#1020
0%
b11011000100 (
b11011000100 +
#1025
b1 ,
b1 /
b1101000010000000000000000000000011011000100 .
1%
#1030
0%
b11011010100 (
b11011010100 +
#1035
b10 ,
b1101100010000000000000000000000011011010100 .
b1101000010000000000000000000000011011000100 $
b1101000010000000000000000000000011011000100 -
1%
#1040
0%
b11011100100 (
b11011100100 +
#1045
b0 ,
1"
0!
b10 /
b1101100010000000000000000000000011011010100 $
b1101100010000000000000000000000011011010100 -
1%
#1050
0%
b11011110100 (
b11011110100 +
